{"_id":{"$oid":"58e7e4e1ec7fbb5eae43d6b1"},"c_id":{"ref":"customer","id":{"$oid":"58e2a79d6d60ab35109d98af"}},"store_id":1.0,"sale":22.93,"amount":1.0,"p_id":{"ref":"product","id":{"$oid":"58e2f7126d60ab35109d98b9"}},"time":"2017-02-15"}
{"_id":{"$oid":"58e7e4e1ec7fbb5eae43d6b2"},"c_id":{"ref":"customer","id":{"$oid":"58e2a79d6d60ab35109d98af"}},"store_id":1.0,"sale":21.03,"amount":1.0,"p_id":{"ref":"product","id":{"$oid":"58e2f7126d60ab35109d98bb"}},"time":"2017-02-15"}
{"_id":{"$oid":"58e7e4e1ec7fbb5eae43d6b3"},"c_id":{"ref":"customer","id":{"$oid":"58e2abe66d60ab35109d98b2"}},"store_id":2.0,"sale":5.03,"amount":1.0,"p_id":{"ref":"product","id":{"$oid":"58e2f7126d60ab35109d98bc"}},"time":"2017-02-18"}
{"_id":{"$oid":"58e7e4e1ec7fbb5eae43d6b4"},"c_id":{"ref":"customer","id":{"$oid":"58e2abe66d60ab35109d98b4"}},"store_id":3.0,"sale":10.06,"amount":2.0,"p_id":{"ref":"product","id":{"$oid":"58e2f7126d60ab35109d98ba"}},"time":"2017-02-19"}
{"_id":{"$oid":"58e7e4e1ec7fbb5eae43d6b5"},"c_id":{"ref":"customer","id":{"$oid":"58e2abe66d60ab35109d98b4"}},"store_id":3.0,"sale":46.96,"amount":2.0,"p_id":{"ref":"product","id":{"$oid":"58e2f7126d60ab35109d98c1"}},"time":"2017-02-22"}
{"_id":{"$oid":"58e7e4e1ec7fbb5eae43d6b6"},"c_id":{"ref":"customer","id":{"$oid":"58e2abe66d60ab35109d98b4"}},"store_id":3.0,"sale":34.18,"amount":2.0,"p_id":{"ref":"product","id":{"$oid":"58e2f7126d60ab35109d98c0"}},"time":"2017-02-24"}
{"_id":{"$oid":"58e7e4e1ec7fbb5eae43d6b7"},"c_id":{"ref":"customer","id":{"$oid":"58e2abe66d60ab35109d98b5"}},"store_id":3.0,"sale":22.7,"amount":2.0,"p_id":{"ref":"product","id":{"$oid":"58e2f7126d60ab35109d98bd"}},"time":"2017-02-24"}
{"_id":{"$oid":"58e7e4e1ec7fbb5eae43d6b8"},"c_id":{"ref":"customer","id":{"$oid":"58e2abe66d60ab35109d98b5"}},"store_id":3.0,"sale":16.14,"amount":2.0,"p_id":{"ref":"product","id":{"$oid":"58e2f7126d60ab35109d98be"}},"time":"2017-02-24"}
{"_id":{"$oid":"58e7e4e1ec7fbb5eae43d6b9"},"c_id":{"ref":"customer","id":{"$oid":"58e2abe66d60ab35109d98b5"}},"store_id":3.0,"sale":8.95,"amount":1.0,"p_id":{"ref":"product","id":{"$oid":"58e2f7126d60ab35109d98bf"}},"time":"2017-02-24"}
{"_id":{"$oid":"58e7e4e1ec7fbb5eae43d6ba"},"c_id":{"ref":"customer","id":{"$oid":"58e2abe66d60ab35109d98b6"}},"store_id":3.0,"sale":21.03,"amount":1.0,"p_id":{"ref":"product","id":{"$oid":"58e2f7126d60ab35109d98bb"}},"time":"2017-02-28"}
{"_id":{"$oid":"58e7e4e1ec7fbb5eae43d6bb"},"c_id":{"ref":"customer","id":{"$oid":"58e2abe66d60ab35109d98b4"}},"store_id":1.0,"sale":32.12,"amount":2.0,"p_id":{"ref":"product","id":{"$oid":"58e2f7126d60ab35109d98bb"}},"time":"2017-02-28"}
{"_id":{"$oid":"58e7e4e1ec7fbb5eae43d6bc"},"c_id":{"ref":"customer","id":{"$oid":"58e2abe66d60ab35109d98b4"}},"store_id":1.0,"sale":46.96,"amount":2.0,"p_id":{"ref":"product","id":{"$oid":"58e2f7126d60ab35109d98c1"}},"time":"2017-02-28"}
{"_id":{"$oid":"58e7e4e1ec7fbb5eae43d6bd"},"c_id":{"ref":"customer","id":{"$oid":"58e2abe66d60ab35109d98b6"}},"store_id":2.0,"sale":22.93,"amount":1.0,"p_id":{"ref":"product","id":{"$oid":"58e2f7126d60ab35109d98b9"}},"time":"2017-02-28"}
{"_id":{"$oid":"58e7e4e1ec7fbb5eae43d6be"},"c_id":{"ref":"customer","id":{"$oid":"58e2abe66d60ab35109d98b6"}},"store_id":2.0,"sale":10.06,"amount":2.0,"p_id":{"ref":"product","id":{"$oid":"58e2f7126d60ab35109d98ba"}},"time":"2017-02-28"}
{"_id":{"$oid":"58e7e4e1ec7fbb5eae43d6bf"},"c_id":{"ref":"customer","id":{"$oid":"58e2abe66d60ab35109d98b6"}},"store_id":2.0,"sale":20.48,"amount":1.0,"p_id":{"ref":"product","id":{"$oid":"58e2f7126d60ab35109d98c2"}},"time":"2017-02-28"}
{"_id":{"$oid":"58e7e4e2ec7fbb5eae43d6c0"},"c_id":{"ref":"customer","id":{"$oid":"58e2abe66d60ab35109d98b4"}},"store_id":1.0,"sale":10.06,"amount":2.0,"p_id":{"ref":"product","id":{"$oid":"58e2f7126d60ab35109d98ba"}},"time":"2017-03-01"}
{"_id":{"$oid":"58e7e4e2ec7fbb5eae43d6c1"},"c_id":{"ref":"customer","id":{"$oid":"58e2a79d6d60ab35109d98af"}},"store_id":1.0,"sale":22.93,"amount":1.0,"p_id":{"ref":"product","id":{"$oid":"58e2f7126d60ab35109d98b9"}},"time":"2017-03-03"}
{"_id":{"$oid":"58e7e4e2ec7fbb5eae43d6c2"},"c_id":{"ref":"customer","id":{"$oid":"58e2abe66d60ab35109d98b3"}},"store_id":1.0,"sale":22.93,"amount":1.0,"p_id":{"ref":"product","id":{"$oid":"58e2f7126d60ab35109d98b9"}},"time":"2017-03-05"}
{"_id":{"$oid":"58e7e4e2ec7fbb5eae43d6c3"},"c_id":{"ref":"customer","id":{"$oid":"58e2abe66d60ab35109d98b4"}},"store_id":3.0,"sale":22.93,"amount":1.0,"p_id":{"ref":"product","id":{"$oid":"58e2f7126d60ab35109d98b9"}},"time":"2017-03-06"}
{"_id":{"$oid":"58e7e4e2ec7fbb5eae43d6c4"},"c_id":{"ref":"customer","id":{"$oid":"58e2abe66d60ab35109d98b4"}},"store_id":3.0,"sale":17.09,"amount":1.0,"p_id":{"ref":"product","id":{"$oid":"58e2f7126d60ab35109d98c0"}},"time":"2017-03-06"}
{"_id":{"$oid":"58e7e4e2ec7fbb5eae43d6c5"},"c_id":{"ref":"customer","id":{"$oid":"58e2abe66d60ab35109d98b2"}},"store_id":3.0,"sale":8.07,"amount":1.0,"p_id":{"ref":"product","id":{"$oid":"58e2f7126d60ab35109d98be"}},"time":"2017-03-07"}
{"_id":{"$oid":"58e7e4e2ec7fbb5eae43d6c6"},"c_id":{"ref":"customer","id":{"$oid":"58e2a79d6d60ab35109d98af"}},"store_id":4.0,"sale":11.35,"amount":1.0,"p_id":{"ref":"product","id":{"$oid":"58e2f7126d60ab35109d98bd"}},"time":"2017-03-13"}
{"_id":{"$oid":"58e7e4e2ec7fbb5eae43d6c7"},"c_id":{"ref":"customer","id":{"$oid":"58e2a79d6d60ab35109d98af"}},"store_id":4.0,"sale":8.07,"amount":1.0,"p_id":{"ref":"product","id":{"$oid":"58e2f7126d60ab35109d98be"}},"time":"2017-03-16"}
{"_id":{"$oid":"58e7e4e2ec7fbb5eae43d6c8"},"c_id":{"ref":"customer","id":{"$oid":"58e2a79d6d60ab35109d98af"}},"store_id":4.0,"sale":16.06,"amount":1.0,"p_id":{"ref":"product","id":{"$oid":"58e2f7126d60ab35109d98bb"}},"time":"2017-03-17"}
{"_id":{"$oid":"58e7e4e2ec7fbb5eae43d6c9"},"c_id":{"ref":"customer","id":{"$oid":"58e2abe66d60ab35109d98b8"}},"store_id":3.0,"sale":16.06,"amount":1.0,"p_id":{"ref":"product","id":{"$oid":"58e2f7126d60ab35109d98bb"}},"time":"2017-03-18"}
{"_id":{"$oid":"58e7e4e2ec7fbb5eae43d6ca"},"c_id":{"ref":"customer","id":{"$oid":"58e2abe66d60ab35109d98b8"}},"store_id":3.0,"sale":17.9,"amount":2.0,"p_id":{"ref":"product","id":{"$oid":"58e2f7126d60ab35109d98bf"}},"time":"2017-03-18"}
{"_id":{"$oid":"58e7e4e2ec7fbb5eae43d6cb"},"c_id":{"ref":"customer","id":{"$oid":"58e2abe66d60ab35109d98b8"}},"store_id":3.0,"sale":25.31,"amount":1.0,"p_id":{"ref":"product","id":{"$oid":"58e2f7126d60ab35109d98c2"}},"time":"2017-03-18"}
{"_id":{"$oid":"58e7e4e2ec7fbb5eae43d6cc"},"c_id":{"ref":"customer","id":{"$oid":"58e2abe66d60ab35109d98b4"}},"store_id":1.0,"sale":10.06,"amount":2.0,"p_id":{"ref":"product","id":{"$oid":"58e2f7126d60ab35109d98ba"}},"time":"2017-03-18"}
{"_id":{"$oid":"58e7e4e2ec7fbb5eae43d6cd"},"c_id":{"ref":"customer","id":{"$oid":"58e2abe66d60ab35109d98b7"}},"store_id":2.0,"sale":8.95,"amount":1.0,"p_id":{"ref":"product","id":{"$oid":"58e2f7126d60ab35109d98bf"}},"time":"2017-03-20"}
